alyahmor/__init__.py
alyahmor/aly_stem_noun_const.py
alyahmor/aly_stem_verb_const.py
alyahmor/basic_affixer.py
alyahmor/genelex.py
alyahmor/noun_affixer.py
alyahmor/stem_noun_const.py
alyahmor/stem_verb_const.py
alyahmor/verb_affixer.py
alyahmor-0.1.4.dist-info/AUTHORS.md
alyahmor-0.1.4.dist-info/LICENSE
alyahmor-0.1.4.dist-info/METADATA
alyahmor-0.1.4.dist-info/WHEEL
alyahmor-0.1.4.dist-info/top_level.txt
alyahmor-0.1.4.dist-info/RECORD
