Metadata-Version: 2.1
Name: alyahmor
Version: 0.1.4
Summary: Alyahmor Arabic Morphological Genrator for Python
Home-page: http://github.com/linuxscout/alyahmor/
Author: Taha Zerrouki
Author-email: taha. zerrouki@gmail .com
License: GPL
Platform: UNKNOWN
Classifier: Development Status :: 5 - Production/Stable
Classifier: Natural Language :: Arabic
Classifier: Intended Audience :: Developers
Classifier: Operating System :: OS Independent
Classifier: Programming Language :: Python
Classifier: Topic :: Text Processing :: Linguistic
Requires-Dist: arramooz-pysqlite (>=0.1)
Requires-Dist: libqutrub (>=1.0)
Requires-Dist: pyarabic (>=0.6.2)
